## Hello.java代码样例

```java
public class ParseDemo {

    int sum;

    public ParseDemo() {
        this.sum = 0;
    }

    public void add(int value) {
        sum += value;
    }

    public void sub(int value) {
        sum -= value;
    }

    public void mul(int value) {
        sum *= value;
    }
    public void div(int value) {
        sum /= value;
    }

    public static void main(String[] args) {
        ParseDemo demo = new ParseDemo();
        if (demo.sum <= 0) {
            demo.add(10);
            demo.sub(1);
            demo.mul(2);
            demo.div(3);
        }

        for (int i = 0; i < demo.sum; i++) {
            demo.sum--;
        }
    }
}
```

## 字节码分析

```bash
 Last modified 2021-1-15; size 730 bytes
  MD5 checksum 25f8f0196891611b76b3ad3ebe4f0a1f
  Compiled from "ParseDemo.java"
public class ParseDemo
  minor version: 0
  major version: 52
  flags: ACC_PUBLIC, ACC_SUPER
Constant pool:
   #1 = Methodref          #9.#27         // java/lang/Object."<init>":()V
   #2 = Fieldref           #3.#28         // ParseDemo.sum:I
   #3 = Class              #29            // ParseDemo
   #4 = Methodref          #3.#27         // ParseDemo."<init>":()V
   #5 = Methodref          #3.#30         // ParseDemo.add:(I)V
   #6 = Methodref          #3.#31         // ParseDemo.sub:(I)V
   #7 = Methodref          #3.#32         // ParseDemo.mul:(I)V
   #8 = Methodref          #3.#33         // ParseDemo.div:(I)V
   #9 = Class              #34            // java/lang/Object
  #10 = Utf8               sum
  #11 = Utf8               I
  #12 = Utf8               <init>
  #13 = Utf8               ()V
  #14 = Utf8               Code
  #15 = Utf8               LineNumberTable
  #16 = Utf8               add
  #17 = Utf8               (I)V
  #18 = Utf8               sub
  #19 = Utf8               mul
  #20 = Utf8               div
  #21 = Utf8               main
  #22 = Utf8               ([Ljava/lang/String;)V
  #23 = Utf8               StackMapTable
  #24 = Class              #29            // ParseDemo
  #25 = Utf8               SourceFile
  #26 = Utf8               ParseDemo.java
  #27 = NameAndType        #12:#13        // "<init>":()V
  #28 = NameAndType        #10:#11        // sum:I
  #29 = Utf8               ParseDemo
  #30 = NameAndType        #16:#17        // add:(I)V
  #31 = NameAndType        #18:#17        // sub:(I)V
  #32 = NameAndType        #19:#17        // mul:(I)V
  #33 = NameAndType        #20:#17        // div:(I)V
  #34 = Utf8               java/lang/Object
{
  int sum;
    descriptor: I
    flags:

  public ParseDemo();
    descriptor: ()V
    flags: ACC_PUBLIC
    Code:
      stack=2, locals=1, args_size=1
         0: aload_0
         1: invokespecial #1                  // Method java/lang/Object."<init>":()V
         4: aload_0
         5: iconst_0
         6: putfield      #2                  // Field sum:I
         9: return
      LineNumberTable:
        line 10: 0
        line 11: 4
        line 12: 9

  public void add(int);
    descriptor: (I)V
    flags: ACC_PUBLIC
    Code:
      stack=3, locals=2, args_size=2
         0: aload_0
         1: dup
         2: getfield      #2                  // Field sum:I
         5: iload_1
         6: iadd
         7: putfield      #2                  // Field sum:I
        10: return
      LineNumberTable:
        line 15: 0
        line 16: 10

  public void sub(int);
    descriptor: (I)V
    flags: ACC_PUBLIC
    Code:
      stack=3, locals=2, args_size=2
         0: aload_0
         1: dup
         2: getfield      #2                  // Field sum:I
         5: iload_1
         6: isub
         7: putfield      #2                  // Field sum:I
        10: return
      LineNumberTable:
        line 19: 0
        line 20: 10

  public void mul(int);
    descriptor: (I)V
    flags: ACC_PUBLIC
    Code:
      stack=3, locals=2, args_size=2
         0: aload_0
         1: dup
         2: getfield      #2                  // Field sum:I
         5: iload_1
         6: imul
         7: putfield      #2                  // Field sum:I
        10: return
      LineNumberTable:
        line 22: 0
        line 23: 10

  public void div(int);
    descriptor: (I)V
    flags: ACC_PUBLIC
    Code:
      stack=3, locals=2, args_size=2
         0: aload_0
         1: dup
         2: getfield      #2                  // Field sum:I
         5: iload_1
         6: idiv
         7: putfield      #2                  // Field sum:I
        10: return
      LineNumberTable:
        line 26: 0
        line 27: 10

  public static void main(java.lang.String[]);
    descriptor: ([Ljava/lang/String;)V
    flags: ACC_PUBLIC, ACC_STATIC
    Code:
      stack=3, locals=3, args_size=1
		 # new一个ParseDemo实例并将实例引用压入栈顶
         0: new           #3                  // class ParseDemo
		 # 复制栈顶实例并压入栈顶
         3: dup
		 # 调用构造方法初始化
         4: invokespecial #4                  // Method "<init>":()V
		 # 将sum存入本地变量1
         7: astore_1
		 # 将sum推到栈顶
         8: aload_1
		 # 获取常量池中槽位为2的值并压入栈顶
         9: getfield      #2                  // Field sum:I
		 # 如果sum > 0 则跳到36 否则继续
        12: ifgt          36
		# 	将sum推到栈顶
        15: aload_1
		# 将10推到栈顶
        16: bipush        10
		# 调用Constant pool中#5的add方法
        18: invokevirtual #5                  // Method add:(I)V
		# 将sum推到栈顶
        21: aload_1
		# 将1推到栈顶
        22: iconst_1
		# 调用Constant pool中#6的sub方法
        23: invokevirtual #6                  # Method sub:(I)V
		# 将sum推到栈顶
        26: aload_1
		# 将2推到栈顶
        27: iconst_2
		# 调用Constant pool中#7的mul方法
        28: invokevirtual #7                  // Method mul:(I)V
		# 将sum推到栈顶
        31: aload_1
		# 将4推到栈顶
        32: iconst_4
		# 调用Constant pool中#8的div方法
        33: invokevirtual #8                  // Method div:(I)V
		
		# 将sum推到栈顶(sum小于36或者执行完了if语句后)
        36: iconst_0
		# 将i的值存入本地变量
        37: istore_2
		#  将i的值推到栈顶
        38: iload_2
		# 将demo推到栈顶
        39: aload_1
		# 获取常量池中槽位为2的值并压入栈顶
        40: getfield      #2                  // Field sum:I
		# 如果i > sum则跳转到62
        43: if_icmpge     62
		# 否则将demo推到栈顶
        46: aload_1
		# 将demo推到栈顶 (demo.sum = demo.sum - 1;)
        47: aload_1
		# 获取sum并推到栈顶
        48: getfield      #2                  // Field sum:I
		# 将1推到栈顶
        51: iconst_1
		# 执行-1操作
        52: isub
		# 为sum赋值
        53: putfield      #2                  // Field sum:I
		# 执行i++
        56: iinc          2, 1
		# 回到38执行循环
        59: goto          38
        62: return
      LineNumberTable:
        line 31: 0
        line 32: 8
        line 33: 15
        line 34: 21
        line 35: 26
        line 36: 31
        line 39: 36
        line 40: 46
        line 39: 56
        line 43: 62
      StackMapTable: number_of_entries = 3
        frame_type = 252 /* append */
          offset_delta = 36
          locals = [ class ParseDemo ]
        frame_type = 252 /* append */
          offset_delta = 1
          locals = [ int ]
        frame_type = 250 /* chop */
          offset_delta = 23
}
```

